odoo/addons/product_variant_configurator/README.rst
odoo/addons/product_variant_configurator/__init__.py
odoo/addons/product_variant_configurator/__manifest__.py
odoo/addons/product_variant_configurator/i18n/am.po
odoo/addons/product_variant_configurator/i18n/ar.po
odoo/addons/product_variant_configurator/i18n/bg.po
odoo/addons/product_variant_configurator/i18n/bs.po
odoo/addons/product_variant_configurator/i18n/ca.po
odoo/addons/product_variant_configurator/i18n/cs.po
odoo/addons/product_variant_configurator/i18n/da.po
odoo/addons/product_variant_configurator/i18n/de.po
odoo/addons/product_variant_configurator/i18n/el_GR.po
odoo/addons/product_variant_configurator/i18n/en_GB.po
odoo/addons/product_variant_configurator/i18n/es.po
odoo/addons/product_variant_configurator/i18n/es_AR.po
odoo/addons/product_variant_configurator/i18n/es_CL.po
odoo/addons/product_variant_configurator/i18n/es_CO.po
odoo/addons/product_variant_configurator/i18n/es_CR.po
odoo/addons/product_variant_configurator/i18n/es_DO.po
odoo/addons/product_variant_configurator/i18n/es_EC.po
odoo/addons/product_variant_configurator/i18n/es_ES.po
odoo/addons/product_variant_configurator/i18n/es_MX.po
odoo/addons/product_variant_configurator/i18n/es_PE.po
odoo/addons/product_variant_configurator/i18n/es_PY.po
odoo/addons/product_variant_configurator/i18n/es_VE.po
odoo/addons/product_variant_configurator/i18n/et.po
odoo/addons/product_variant_configurator/i18n/eu.po
odoo/addons/product_variant_configurator/i18n/fa.po
odoo/addons/product_variant_configurator/i18n/fi.po
odoo/addons/product_variant_configurator/i18n/fr.po
odoo/addons/product_variant_configurator/i18n/fr_CA.po
odoo/addons/product_variant_configurator/i18n/fr_CH.po
odoo/addons/product_variant_configurator/i18n/gl.po
odoo/addons/product_variant_configurator/i18n/gl_ES.po
odoo/addons/product_variant_configurator/i18n/he.po
odoo/addons/product_variant_configurator/i18n/hr.po
odoo/addons/product_variant_configurator/i18n/hr_HR.po
odoo11_addon_product_variant_configurator-11.0.1.0.0.99.dev24.dist-info/METADATA
odoo11_addon_product_variant_configurator-11.0.1.0.0.99.dev24.dist-info/WHEEL
odoo11_addon_product_variant_configurator-11.0.1.0.0.99.dev24.dist-info/top_level.txt
odoo11_addon_product_variant_configurator-11.0.1.0.0.99.dev24.dist-info/RECORD
